skits/__init__.py
skits/feature_extraction.py
skits/pipeline.py
skits/preprocessing.py
skits-0.1.2.dist-info/LICENSE
skits-0.1.2.dist-info/METADATA
skits-0.1.2.dist-info/WHEEL
skits-0.1.2.dist-info/top_level.txt
skits-0.1.2.dist-info/RECORD
