Metadata-Version: 2.1
Name: skits
Version: 0.1.2
Summary: scikit-learn-inspired time series
Home-page: https://github.com/EthanRosenthal/skits
Author: Ethan Rosenthal
Author-email: ethanrosenthal@gmail.com
License: MIT
Keywords: machine learning time series forecasting
Platform: UNKNOWN
Classifier: Development Status :: 3 - Alpha
Classifier: Intended Audience :: Developers
Classifier: Topic :: Scientific/Engineering :: Information Analysis
Classifier: License :: OSI Approved :: MIT License
Classifier: Programming Language :: Python :: 3
Requires-Dist: numpy
Requires-Dist: scikit-learn
